grayscalelib/napari/__init__.py
grayscalelib/napari/view.py
grayscalelib/napari/tests/test_view.py
grayscalelib_napari-0.0.2.dist-info/METADATA
grayscalelib_napari-0.0.2.dist-info/WHEEL
grayscalelib_napari-0.0.2.dist-info/top_level.txt
grayscalelib_napari-0.0.2.dist-info/RECORD
