Metadata-Version: 2.2
Name: grayscalelib.napari
Version: 0.0.2
Summary: View grayscalelib Pixels with Napari.
Author: Marco Heisig
License: GPL-3.0-or-later
Project-URL: Repository, https://github.com/SandoghdarLab/grayscalelib.matplotlib.git
Keywords: grayscale,video,image,pixel,napari
Requires-Python: >=3.11
Requires-Dist: grayscalelib.core
Requires-Dist: numpy
Requires-Dist: napari[pyqt5]
Provides-Extra: dev
Requires-Dist: isort; extra == "dev"
Requires-Dist: ruff; extra == "dev"
Requires-Dist: pre-commit; extra == "dev"
Provides-Extra: test
Requires-Dist: pytest; extra == "test"
